powerplantmatching/__init__.py
powerplantmatching/accessor.py
powerplantmatching/cleaning.py
powerplantmatching/collection.py
powerplantmatching/core.py
powerplantmatching/data.py
powerplantmatching/duke.py
powerplantmatching/export.py
powerplantmatching/heuristics.py
powerplantmatching/matching.py
powerplantmatching/plot.py
powerplantmatching/utils.py
powerplantmatching/package_data/Comparison.xml
powerplantmatching/package_data/Deleteduplicates.xml
powerplantmatching/package_data/PLZ_Coords_map.csv
powerplantmatching/package_data/config.yaml
powerplantmatching/package_data/country_codes.csv
powerplantmatching/package_data/entsoe_country_codes.csv
powerplantmatching/package_data/manual_corrections.csv
powerplantmatching/package_data/manual_corrections_old.csv
powerplantmatching/package_data/parsed_locations.csv
powerplantmatching/package_data/duke_binaries/duke-core-1.3-SNAPSHOT-tests.jar
powerplantmatching/package_data/duke_binaries/duke-core-1.3-SNAPSHOT.jar
powerplantmatching/package_data/duke_binaries/duke-es-1.3-SNAPSHOT.jar
powerplantmatching/package_data/duke_binaries/duke-json-1.3-SNAPSHOT.jar
powerplantmatching/package_data/duke_binaries/duke-lucene-1.3-SNAPSHOT.jar
powerplantmatching/package_data/duke_binaries/duke-mapdb-1.3-SNAPSHOT.jar
powerplantmatching/package_data/duke_binaries/duke-mongodb-1.3-SNAPSHOT.jar
powerplantmatching/package_data/duke_binaries/duke-server-1.3-SNAPSHOT.jar
powerplantmatching-0.8.0.dist-info/METADATA
powerplantmatching-0.8.0.dist-info/WHEEL
powerplantmatching-0.8.0.dist-info/top_level.txt
powerplantmatching-0.8.0.dist-info/RECORD
