Metadata-Version: 2.4
Name: powerplantmatching
Version: 0.8.0
Summary: Toolset for generating and managing Power Plant Data
Author: Jonas Hoersch (KIT), Fabian Gotzens (FZ Jülich)
Author-email: "Fabian Hofmann (FIAS)" <fabianmarikhofmann@gmail.com>
Project-URL: Homepage, https://github.com/PyPSA/powerplantmatching
Project-URL: Source, https://github.com/PyPSA/powerplantmatching
Classifier: Programming Language :: Python :: 3.10
Classifier: Programming Language :: Python :: 3.11
Classifier: Programming Language :: Python :: 3.12
Classifier: Programming Language :: Python :: 3.13
Classifier: Environment :: Console
Classifier: Intended Audience :: Science/Research
Classifier: License :: OSI Approved :: MIT License
Classifier: Natural Language :: English
Classifier: Operating System :: OS Independent
Requires-Python: >=3.10
Requires-Dist: numpy
Requires-Dist: scipy
Requires-Dist: pandas>=0.24.0
Requires-Dist: networkx>=1.10
Requires-Dist: pycountry
Requires-Dist: country_converter
Requires-Dist: xlrd
Requires-Dist: seaborn
Requires-Dist: pyyaml>=5.1.0
Requires-Dist: requests
Requires-Dist: matplotlib
Requires-Dist: geopy
Requires-Dist: xlrd
Requires-Dist: unidecode
Requires-Dist: entsoe-py>=0.3.1
Requires-Dist: deprecation
Requires-Dist: tqdm
Requires-Dist: openpyxl
Provides-Extra: docs
Requires-Dist: mkdocs-material; extra == "docs"
Requires-Dist: mkdocs-ezlinks-plugin; extra == "docs"
Requires-Dist: mkdocs-autolinks-plugin; extra == "docs"
Requires-Dist: mkdocs-redirects; extra == "docs"
Requires-Dist: mkdocs-video; extra == "docs"
Requires-Dist: mkdocs-git-revision-date-localized-plugin; extra == "docs"
Requires-Dist: mkdocs-git-committers-plugin; extra == "docs"
Requires-Dist: mkdocs-argref-plugin; extra == "docs"
Requires-Dist: mkdocs-table-reader-plugin; extra == "docs"
Requires-Dist: mkdocstrings-python; extra == "docs"
Requires-Dist: mkdocs-jupyter; extra == "docs"
Requires-Dist: cairosvg; extra == "docs"
Requires-Dist: pillow; extra == "docs"
Provides-Extra: dev
Requires-Dist: pre-commit; extra == "dev"
Requires-Dist: pytest; extra == "dev"
Requires-Dist: pytest-cov; extra == "dev"
Requires-Dist: mypy; extra == "dev"
Requires-Dist: types-requests; extra == "dev"
Requires-Dist: types-PyYAML; extra == "dev"
Requires-Dist: pandas-stubs; extra == "dev"
Requires-Dist: types-tqdm; extra == "dev"
Requires-Dist: types-six; extra == "dev"
Requires-Dist: reuse>=5.0.2; extra == "dev"
Provides-Extra: plotting
Requires-Dist: cartopy; extra == "plotting"
